rayvision_sync/__init__.py
rayvision_sync/constants.py
rayvision_sync/db_config.ini
rayvision_sync/download.py
rayvision_sync/exception.py
rayvision_sync/manage.py
rayvision_sync/transfer.py
rayvision_sync/upload.py
rayvision_sync/utils.py
rayvision_sync/rayvision_raysync/__init__.py
rayvision_sync/rayvision_raysync/constants.py
rayvision_sync/rayvision_raysync/exception.py
rayvision_sync/rayvision_raysync/transfer_raysync.py
rayvision_sync/rayvision_raysync/url.py
rayvision_sync/rayvision_raysync/utils.py
rayvision_sync/tests/__init__.py
rayvision_sync/tests/conftest.py
rayvision_sync/tests/test_download.py
rayvision_sync/tests/test_manage.py
rayvision_sync/tests/test_transfer.py
rayvision_sync/tests/test_upload.py
rayvision_sync/tests/test_utils.py
rayvision_sync/transmission/db.ini
rayvision_sync/transmission/transports.json
rayvision_sync/transmission/usage.txt
rayvision_sync/transmission/linux/rayvision_transmitter
rayvision_sync/transmission/linux/aspera/ascmd
rayvision_sync/transmission/linux/aspera/ascp
rayvision_sync/transmission/linux/aspera/aspera-license
rayvision_sync/transmission/linux/aspera/aspshell
rayvision_sync/transmission/linux/aspera/astokengen
rayvision_sync/transmission/linux/raysync/killproxy.sh
rayvision_sync/transmission/linux/raysync/raysyncproxy
rayvision_sync/transmission/windows/RaySync-Multi-Proxy-Client.dll
rayvision_sync/transmission/windows/RaySync.dll
rayvision_sync/transmission/windows/aes_ecb.dll
rayvision_sync/transmission/windows/aspera_engine.dll
rayvision_sync/transmission/windows/cmarkup.dll
rayvision_sync/transmission/windows/hiredis.dll
rayvision_sync/transmission/windows/json.dll
rayvision_sync/transmission/windows/libAuthentication.dll
rayvision_sync/transmission/windows/libjson.dll
rayvision_sync/transmission/windows/libsqlite.dll
rayvision_sync/transmission/windows/raysync_engine.dll
rayvision_sync/transmission/windows/rayvision_transmitter.exe
rayvision_sync/transmission/windows/stupid_base.dll
rayvision_sync-3.1.7.dist-info/LICENSE
rayvision_sync-3.1.7.dist-info/METADATA
rayvision_sync-3.1.7.dist-info/WHEEL
rayvision_sync-3.1.7.dist-info/top_level.txt
rayvision_sync-3.1.7.dist-info/RECORD
