Metadata-Version: 2.1
Name: rayvision-sync
Version: 3.1.7
Summary: Upload configuration file and asset file, download result file.
Home-page: https://github.com/renderbus/rayvision_sync
Author: Shenzhen Rayvision Technology Co., Ltd
Author-email: developer@rayvision.com
Classifier: Programming Language :: Python
Classifier: Programming Language :: Python :: 2
Classifier: Programming Language :: Python :: 3
License-File: LICENSE
Requires-Dist: rayvision-log >=0.3.3
Requires-Dist: rayvision-api >=1.1.0
Requires-Dist: requests ==2.23.0
Requires-Dist: configparser ==4.0.2
Requires-Dist: tenacity ==7.0.0
Requires-Dist: tqdm ==4.64.1
